nure_tools.py
nure_tools-1.7.0.dist-info/LICENSE
nure_tools-1.7.0.dist-info/WHEEL
nure_tools-1.7.0.dist-info/METADATA
nure_tools-1.7.0.dist-info/RECORD
