Metadata-Version: 2.1
Name: nure_tools
Version: 1.7.0
Summary: Simple pyton library for nure-cist API
Author-email: pencel_z_kavunom <soappguy@gmail.com>
Requires-Python: >=3.10
Classifier: License :: OSI Approved :: GNU General Public License v3 or later (GPLv3+)
Requires-Dist: requests >=2.31.0
Project-URL: Home, https://github.com/SoappGuy/nure_tools
